[
  {
    "id": "narrative",
    "label": "MARKET_NARRATIVE",
    "value": "STABLECOIN_REGULATION_NEARS_IMPLEMENTATION",
    "description": "Stablecoin regulation nearing implementation influences market dynamics and institutional strategies.",
    "status": "NEUTRAL",
    "related_url": "https://www.htx.com/en-in/news/Research%20%26%20Analysis-S5l8Y8SM/",
    "updated_at": "2026-06-11T00:00:00Z"
  },
  {
    "id": "sentiment",
    "label": "MARKET_SENTIMENT",
    "value": "EXTREME_FEAR",
    "description": "Market sentiment remains in extreme fear territory, indicating sustained pessimism among investors.",
    "status": "BEARISH",
    "related_url": "https://coinstats.app/ai/a/crypto-news-update-11-June-2026",
    "updated_at": "2026-06-11T00:00:00Z"
  },
  {
    "id": "rotation",
    "label": "CAPITAL_ROTATION",
    "value": "SHIFT_TO_PAYMENT_INFRASTRUCTURE",
    "description": "Capital is rotating towards payment infrastructure and cash flow markets, indicating a defensive positioning.",
    "status": "NEUTRAL",
    "related_url": "https://www.htx.com/en-in/news/Research%20%26%20Analysis-S5l8Y8SM/",
    "updated_at": "2026-06-11T00:00:00Z"
  },
  {
    "id": "risk",
    "label": "RISK_APPETITE",
    "value": "DELEVERAGING_TREND",
    "description": "A trend of deleveraging is observed, with open interest and funding rates declining, indicating reduced risk appetite.",
    "status": "BEARISH",
    "related_url": "https://coinstats.app/ai/a/crypto-news-update-11-June-2026",
    "updated_at": "2026-06-11T00:00:00Z"
  },
  {
    "id": "institutional",
    "label": "INSTITUTIONAL_FOCUS",
    "value": "STABLECOIN_INFRASTRUCTURE_AND_AI_AGENT_FUNDING",
    "description": "Institutional focus is on stablecoin infrastructure and AI agent projects, with significant funding in these areas.",
    "status": "BULLISH",
    "related_url": "https://www.htx.com/en-in/news/Research%20%26%20Analysis-S5l8Y8SM/",
    "updated_at": "2026-06-11T00:00:00Z"
  }
]